CHANGELOG.md
LICENSE
MANIFEST.in
README.md
requirements.txt
setup.py
libsonic/__init__.py
libsonic/connection.py
libsonic/errors.py
py_sonic.egg-info/PKG-INFO
py_sonic.egg-info/SOURCES.txt
py_sonic.egg-info/dependency_links.txt
py_sonic.egg-info/top_level.txt